aiosparql/__init__.py
aiosparql/client.py
aiosparql/escape.py
aiosparql/syntax.py
aiosparql/test_utils.py
aiosparql-0.12.0.dist-info/LICENSE
aiosparql-0.12.0.dist-info/METADATA
aiosparql-0.12.0.dist-info/WHEEL
aiosparql-0.12.0.dist-info/top_level.txt
aiosparql-0.12.0.dist-info/RECORD
