Metadata-Version: 2.1
Name: aiosparql
Version: 0.12.0
Summary: An asynchronous SPARQL library using aiohttp
Home-page: https://github.com/aio-libs/aiosparql
Maintainer: Cecile Tonglet
Maintainer-email: cecile.tonglet@gmail.com
License: Apache 2
Platform: UNKNOWN
Classifier: Development Status :: 3 - Alpha
Classifier: Environment :: Other Environment
Classifier: Intended Audience :: Developers
Classifier: Operating System :: OS Independent
Classifier: Programming Language :: Python
Classifier: Programming Language :: Python :: 3 :: Only
Classifier: Programming Language :: Python :: 3.6
Classifier: Programming Language :: Python :: 3.7
Classifier: Programming Language :: Python :: 3.8
Classifier: Programming Language :: Python :: 3.9
Classifier: Topic :: Utilities
Classifier: License :: OSI Approved :: Apache Software License
Requires-Python: >=3.6.0
Requires-Dist: aiohttp (>=3.5.0)
